streamers/__init__.py
streamers/streamers.py
tests/__init__.py
tests/streamers_test.py
streamers-1.3.3.dist-info/LICENSE
streamers-1.3.3.dist-info/METADATA
streamers-1.3.3.dist-info/WHEEL
streamers-1.3.3.dist-info/entry_points.txt
streamers-1.3.3.dist-info/top_level.txt
streamers-1.3.3.dist-info/RECORD
