Metadata-Version: 2.1
Name: streamers
Version: 1.3.3
Summary: A CLI tool to see who you follow on twitch is streaming and watch them.
Home-page: https://github.com/nbgibson/streamers
Author: Nate Gibson
Author-email: natebgibson@gmail.com
Classifier: Programming Language :: Python :: 3
Classifier: License :: OSI Approved :: MIT License
Classifier: Operating System :: OS Independent
Requires-Python: >=3.7
License-File: LICENSE
Requires-Dist: requests >=2.26.0
Requires-Dist: streamlink >=5.3.0
